CHANGELOG.rst
LICENSE
MANIFEST.in
README.md
homura.py
requirements.txt
setup.py
homura.egg-info/PKG-INFO
homura.egg-info/SOURCES.txt
homura.egg-info/dependency_links.txt
homura.egg-info/not-zip-safe
homura.egg-info/requires.txt
homura.egg-info/top_level.txt