Metadata-Version: 1.1
Name: homura
Version: 0.1.5
Summary: Python downloader with progress
Home-page: https://github.com/shichao-an/homura
Author: Shichao An
Author-email: shichao.an@nyu.edu
License: BSD
Keywords: download progress
Platform: UNKNOWN
Classifier: License :: OSI Approved :: BSD License
Classifier: Programming Language :: Python
Classifier: Programming Language :: Python :: 2
Classifier: Programming Language :: Python :: 3
